passjoin/__init__.py
passjoin/passjoin.py
passjoin-0.0.1.dist-info/LICENSE
passjoin-0.0.1.dist-info/METADATA
passjoin-0.0.1.dist-info/WHEEL
passjoin-0.0.1.dist-info/top_level.txt
passjoin-0.0.1.dist-info/RECORD
