Metadata-Version: 2.1
Name: passjoin
Version: 0.0.1
Summary: Python implementation of the Pass-join index
Home-page: https://github.com/mapado/passjoin
Author: Romain SENESI
Author-email: romain.senesi@mapado.com
Maintainer: Romain SENESI
Maintainer-email: romain.senesi@mapado.com
License: ['MIT']
Platform: UNKNOWN
Classifier: Development Status :: 4 - Beta
Classifier: Intended Audience :: Developers
Classifier: License :: OSI Approved :: MIT License
Classifier: Programming Language :: Python
Classifier: Programming Language :: Python :: 3
Classifier: Topic :: Software Development :: Libraries :: Python Modules
